{
  "query_string": "The Mourning Bride",
  "difficulties": [
    5,
    6,
    7,
    8,
    9,
    10
  ],
  "min_year": 2012,
  "answer_matches": {
    "tossups": [],
    "bonuses": [
      {
        "_id": "6334baae3df8739d684ba9e7",
        "leadin": "This play's opening claims that \"music has charms to soothe a savage breast.\" For 10 points each:",
        "parts": [
          "Name this only tragedy by William Congreve, which elsewhere notes that \"heav'n has no rage, like love to hatred turn'd.\"",
          "The Mourning Bride is now best remembered for an oft-misquoted phrase from Act 3, Scene 2, which notes that hell has \"no fury\" like one of these people. A specific two-word phrase is required.",
          "The Mourning Bride exemplifies this period's theater. William Wycherley's The Country Wife is one of the \"comedies\" named for this period, during which Charles II returned to the throne."
        ],
        "answers": [
          "The <b><u>Mourning Bride</u></b>",
          "a <b><u>woman scorn'd</u></b> [or \"nor hell a fury, like a <b><u>woman scorn'd</u></b>\"]",
          "<b><u>Restoration</u></b> theater [or <b><u>Restoration</u></b> period; or <b><u>Restoration</u></b> comedy; or <b><u>Restoration</u></b> drama]"
        ],
        "subcategory": "British Literature",
        "category": "Literature",
        "packet": {
          "_id": "6334baae3df8739d684ba9c6",
          "name": "09",
          "number": 9
        },
        "set": {
          "_id": "6334baae3df8739d684ba86d",
          "name": "2022 NASAT",
          "year": 2022,
          "standard": true
        },
        "updatedAt": "2023-04-09T06:00:05.487Z",
        "difficulty": 8,
        "alternate_subcategory": "Drama",
        "number": 12,
        "answers_sanitized": [
          "The Mourning Bride",
          "a woman scorn'd [or \"nor hell a fury, like a woman scorn'd\"]",
          "Restoration theater [or Restoration period; or Restoration comedy; or Restoration drama]"
        ],
        "leadin_sanitized": "This play's opening claims that \"music has charms to soothe a savage breast.\" For 10 points each:",
        "parts_sanitized": [
          "Name this only tragedy by William Congreve, which elsewhere notes that \"heav'n has no rage, like love to hatred turn'd.\"",
          "The Mourning Bride is now best remembered for an oft-misquoted phrase from Act 3, Scene 2, which notes that hell has \"no fury\" like one of these people. A specific two-word phrase is required.",
          "The Mourning Bride exemplifies this period's theater. William Wycherley's The Country Wife is one of the \"comedies\" named for this period, during which Charles II returned to the throne."
        ]
      }
    ],
    "tossups_found": 0,
    "bonuses_found": 1
  }
}