{
  "topic": "Oskar Kokoschka",
  "summary": "Austrian Expressionist painter and playwright. Most commonly identified by The Bride of the Wind (The Tempest), depicting himself and Alma Mahler. Known for the infamous life-size sex doll of Alma. Also a playwright: Murderer, Hope of Women; Orpheus and Eurydice. Student of Klimt; Vienna Secession.",
  "category": "Fine Arts",
  "subcategory": "Visual Fine Arts",
  "year": 1886,
  "continent": "Europe",
  "country": "Austria",
  "tags": [
    "Expressionism",
    "Vienna Secession"
  ],
  "works": [
    {
      "name": "The Bride of the Wind / The Tempest (1914)",
      "indicator": "Painting",
      "description": "Shows Kokoschka lying wide awake as dark waves swirl around him, with sleeping Alma Mahler in his arms. Based on their tempestuous affair.",
      "images": [
        {
          "url": "",
          "link": "https://en.wikipedia.org/wiki/The_Bride_of_the_Wind",
          "caption": "The Bride of the Wind (1914)"
        }
      ],
      "clues": [
        {
          "clue": "Dark waves swirl around him as he lies wide awake with his sleeping lover (Alma Mahler) in his arms",
          "frequency": 5,
          "tendency": "giveaway",
          "examples": [
            "dark waves swirl around him as he lies wide awake with his sleeping lover in his arms",
            "The Bride of the Wind shows him sleeping next to Alma Mahler"
          ]
        }
      ]
    },
    {
      "name": "General / Biographical",
      "indicator": "Artist",
      "description": "How Kokoschka is identified and biographical clues.",
      "clues": [
        {
          "clue": "Austrian Expressionist; affair with Alma Mahler",
          "frequency": 6,
          "tendency": "giveaway",
          "examples": [
            "this Austrian Expressionist whose affair with Alma Mahler was the basis for his The Bride of the Wind"
          ]
        },
        {
          "clue": "Commissioned a life-size sex doll of Alma Mahler; decapitated it drunkenly at a party",
          "frequency": 3,
          "tendency": "mid",
          "examples": [
            "commissioned a notorious life-size sex doll of the other",
            "drunkenly decapitated a life-sized doll in her likeness at a party"
          ]
        },
        {
          "clue": "Self-Portrait as Knight Errant: sphinx at right of stormy landscape; inspired by Alma's abortion",
          "frequency": 1,
          "tendency": "power",
          "examples": [
            "A sphinx appears at the right of a stormy landscape in a self-portrait of this man as the titular Knight Errant, inspired by his lover's abortion"
          ]
        },
        {
          "clue": "The Dreaming Boys: lithograph series of sexual awakening in pastel colors",
          "frequency": 1,
          "tendency": "mid",
          "examples": [
            "used pastel red, blue, green, and yellow for a lithograph series illustrating sexual awakening, entitled The Dreaming Boys"
          ]
        },
        {
          "clue": "Murderer, Hope of Women (play): 'The Man' is stabbed by 'The Woman' after entering a dark tower; Man kills Woman with a single touch",
          "frequency": 1,
          "tendency": "power",
          "examples": [
            "\"The Man\" is stabbed by \"The Woman\" after he and his Warriors enter a dark tower, but Man breaks free from his cage and kills Woman with a single touch"
          ]
        },
        {
          "clue": "Student of Klimt; painted portraits for architect Adolf Loos's clients",
          "frequency": 1,
          "tendency": "mid",
          "examples": [
            "a student of Klimt, painted a later portrait of Adele's husband Ferdinand as well as many portraits of the clients of architect Adolf Loos"
          ]
        },
        {
          "clue": "Vienna Secession member; art deemed 'degenerate' by Nazis",
          "frequency": 2,
          "tendency": "mid",
          "examples": [
            "Beckmann's art was deemed \"degenerate,\" as was the art of this Viennese artist"
          ]
        },
        {
          "clue": "Painting of Queen Victoria holding a frog and riding a shark; British sailors drown, octopus carries trident",
          "frequency": 1,
          "tendency": "power",
          "examples": [
            "An octopus carries away a trident and some British sailors drown in a painting by this artist in which Queen Victoria holds a frog and rides a shark"
          ]
        },
        {
          "clue": "Wrote play Orpheus and Eurydice (adapted into opera by Ernst Krenek) after WWI service in Ukraine",
          "frequency": 1,
          "tendency": "power",
          "examples": [
            "After serving in Ukraine during World War I, he wrote a play converted into an opera by Ernst Krenek about Orpheus and Eurydice"
          ]
        },
        {
          "clue": "Play Hiob/Job adapted from earlier Sphinx and Strawman; Mr. Rubberman emerges from dog's skin",
          "frequency": 1,
          "tendency": "power",
          "examples": [
            "sees Mr. Rubberman emerge from a dog's skin before confronting the title character"
          ]
        },
        {
          "clue": "O Eternity, Thou Word of Thunder; Loreley; Bach cantata-inspired series Fear guides to the grave",
          "frequency": 1,
          "tendency": "power",
          "examples": [
            "Fear guides this man, as Hope, to his grave in a series he drew after hearing a friend play a Bach cantata"
          ]
        },
        {
          "clue": "Seven Chinese fans documenting Italy trip with Alma; last thrown into fire in jealous fit",
          "frequency": 1,
          "tendency": "power",
          "examples": [
            "A journey to Italy...is documented in the third of a series of seven Chinese fans, the last of which was thrown into a fire in a fit of jealousy"
          ]
        },
        {
          "clue": "Kept blood-stained cotton pad from Alma's abortion until his death; later proposed making a puppet with erect penis for 80-year-old Alma",
          "frequency": 1,
          "tendency": "power",
          "examples": [
            "kept in his possession a blood-stained cotton pad the other used when she had an abortion",
            "When one of these people was 80 years old, the other wrote to her proposing he make a wooden puppet of himself equipped with an erect penis"
          ]
        }
      ]
    }
  ],
  "recursive_suggestions": [
    "Alma Mahler — cross-topic figure (married Gustav Mahler, Walter Gropius)",
    "Vienna Secession — cross-topic with Klimt, Moser"
  ],
  "comprehensive_summary": "Oskar Kokoschka was an Austrian Expressionist painter and playwright. His most famous painting, The Bride of the Wind (also called The Tempest, 1914), shows him lying wide awake with dark waves swirling around him as sleeping Alma Mahler rests in his arms. Their tempestuous affair produced many works and incidents: he commissioned a life-size sex doll of Alma, which he drunkenly decapitated at a party. He kept a blood-stained cotton pad from Alma's abortion until his death. When Alma was 80, he proposed making a wooden puppet of himself with an erect penis. A series of seven Chinese fans documented their Italian journey, the last thrown into fire in jealousy.\n\nHis Self-Portrait as Knight Errant features a sphinx in a stormy landscape, inspired by Alma's abortion. The Dreaming Boys is a lithograph series of sexual awakening. He painted Queen Victoria holding a frog and riding a shark while British sailors drown. He was a student of Klimt and painted portraits for architect Adolf Loos's clients. He was a Vienna Secession member whose art was deemed 'degenerate.'\n\nAs a playwright, Kokoschka wrote Murderer, Hope of Women (in which 'The Man' kills 'The Woman' with a single touch) and Hiob/Job (adapted from Sphinx and Strawman). His play about Orpheus and Eurydice was converted into an opera by Ernst Krenek.",
  "links": [
    {
      "text": "Oskar Kokoschka — Wikipedia",
      "url": "https://en.wikipedia.org/wiki/Oskar_Kokoschka"
    },
    {
      "text": "The Bride of the Wind — Wikipedia",
      "url": "https://en.wikipedia.org/wiki/The_Bride_of_the_Wind"
    }
  ],
  "cards": [
    {
      "type": "basic",
      "indicator": "Painting",
      "front": "Painting: dark waves swirl around the artist as he lies wide awake with his sleeping lover in his arms",
      "back": "The Bride of the Wind (Oskar Kokoschka)",
      "work": "The Bride of the Wind / The Tempest (1914)",
      "frequency": 5,
      "tags": [],
      "images": []
    },
    {
      "type": "image",
      "indicator": "Painting",
      "front": "",
      "back": "The Bride of the Wind (Oskar Kokoschka)",
      "work": "The Bride of the Wind / The Tempest (1914)",
      "frequency": 0,
      "tags": [],
      "images": []
    },
    {
      "type": "basic",
      "indicator": "Artist",
      "front": "Artist: commissioned a life-size sex doll of Alma Mahler, which he drunkenly decapitated at a party",
      "back": "Oskar Kokoschka",
      "work": "General / Biographical",
      "frequency": 3,
      "tags": [],
      "images": []
    },
    {
      "type": "basic",
      "indicator": "Artist",
      "front": "Artist: lithograph series The Dreaming Boys illustrates sexual awakening in pastel colors",
      "back": "Oskar Kokoschka",
      "work": "General / Biographical",
      "frequency": 1,
      "tags": [],
      "images": []
    },
    {
      "type": "basic",
      "indicator": "Artist",
      "front": "Artist: wrote the play Murderer, Hope of Women in which 'The Man' kills 'The Woman' with a single touch",
      "back": "Oskar Kokoschka",
      "work": "General / Biographical",
      "frequency": 1,
      "tags": [],
      "images": []
    },
    {
      "type": "basic",
      "indicator": "Artist",
      "front": "Artist: painted Queen Victoria holding a frog and riding a shark while British sailors drown and an octopus carries a trident",
      "back": "Oskar Kokoschka",
      "work": "General / Biographical",
      "frequency": 1,
      "tags": [],
      "images": []
    }
  ],
  "cross_refs": [
    {
      "name": "Beckmann",
      "target_topic": "Max Beckmann",
      "target_slug": "max_beckmann",
      "target_work": null,
      "type": "topic",
      "exists": true
    }
  ],
  "cache_file": "oskar_kokoschka_d5_6_7_8_9_10_y2012.json"
}