[
  {
    "type": "basic",
    "indicator": "Work",
    "front": "Work: the narrator recites Dante's 'Canto of Ulysses' to Jean (Pikolo) while fetching soup, comparing it to 'the blast of a trumpet, the voice of God'",
    "back": "If This Is a Man / Survival in Auschwitz (Primo Levi)",
    "work": "If This Is a Man / Survival in Auschwitz",
    "frequency": 5,
    "tags": []
  },
  {
    "type": "basic",
    "indicator": "Work",
    "front": "Work: uses 'Lager' for the camp and 'Ka-Be' for the infirmary where nurses confiscate spoons from the ill",
    "back": "If This Is a Man / Survival in Auschwitz (Primo Levi)",
    "work": "If This Is a Man / Survival in Auschwitz",
    "frequency": 3,
    "tags": []
  },
  {
    "type": "basic",
    "indicator": "Work",
    "front": "Work: the narrator is told 'there is no why here' after having an icicle confiscated",
    "back": "If This Is a Man / Survival in Auschwitz (Primo Levi)",
    "work": "If This Is a Man / Survival in Auschwitz",
    "frequency": 1,
    "tags": []
  },
  {
    "type": "basic",
    "indicator": "Work",
    "front": "Work: opening poem addresses 'you who live safe in your warm houses'; commands 'carve them into your hearts'; consider a woman 'without hair and without name'",
    "back": "If This Is a Man / Survival in Auschwitz (Primo Levi)",
    "work": "If This Is a Man / Survival in Auschwitz",
    "frequency": 3,
    "tags": []
  },
  {
    "type": "basic",
    "indicator": "Work",
    "front": "Work: a French girl tells the narrator 'bite your lip, little brother' after he is beaten in an electrical warehouse",
    "back": "If This Is a Man / Survival in Auschwitz (Primo Levi)",
    "work": "If This Is a Man / Survival in Auschwitz",
    "frequency": 1,
    "tags": []
  },
  {
    "type": "basic",
    "indicator": "Work",
    "front": "Work: closes with a meditation paralleling the Jewish V'ahavta; bricklayer Lorenzo smuggled food to the narrator",
    "back": "If This Is a Man / Survival in Auschwitz (Primo Levi)",
    "work": "If This Is a Man / Survival in Auschwitz",
    "frequency": 1,
    "tags": []
  },
  {
    "type": "basic",
    "indicator": "Work",
    "front": "Work: 'Cerium' -- the narrator steals iron-cerium from a factory to make cigarette lighters, buying two months of bread",
    "back": "The Periodic Table (Primo Levi)",
    "work": "The Periodic Table",
    "frequency": 3,
    "tags": []
  },
  {
    "type": "basic",
    "indicator": "Work",
    "front": "Work: 'Vanadium' -- the narrator recognizes former colleague Dr. Muller from his spelling of 'naphthenate' in a letter about defective varnish",
    "back": "The Periodic Table (Primo Levi)",
    "work": "The Periodic Table",
    "frequency": 3,
    "tags": []
  },
  {
    "type": "basic",
    "indicator": "Work",
    "front": "Work: 'Carbon' -- final story narrating the cyclical journey of a single carbon atom",
    "back": "The Periodic Table (Primo Levi)",
    "work": "The Periodic Table",
    "frequency": 2,
    "tags": []
  },
  {
    "type": "basic",
    "indicator": "Work",
    "front": "Work: 'Silver' -- set on the fictional island of Desolation with Welsh place names like Holywell Cave and Mt. Snowdon",
    "back": "The Periodic Table (Primo Levi)",
    "work": "The Periodic Table",
    "frequency": 2,
    "tags": []
  },
  {
    "type": "basic",
    "indicator": "Work",
    "front": "Work: 'Nitrogen' -- contains the line 'matter is matter, neither noble nor vile, infinitely transformable'",
    "back": "The Periodic Table (Primo Levi)",
    "work": "The Periodic Table",
    "frequency": 1,
    "tags": []
  },
  {
    "type": "basic",
    "indicator": "Work",
    "front": "Work: coined the term 'Gray Zone'; places Chaim Rumkowski of Lodz in it; includes 'Letters from Germans' and 'The Memory of the Offense'",
    "back": "The Drowned and the Saved (Primo Levi)",
    "work": "The Drowned and the Saved",
    "frequency": 2,
    "tags": []
  },
  {
    "type": "basic",
    "indicator": "Author",
    "front": "Author: had difficulty finding a thesis advisor due to anti-Semitic laws; worked analyzing mine residues and researching diabetes",
    "back": "Primo Levi",
    "work": "General / Biographical",
    "frequency": 2,
    "tags": []
  },
  {
    "type": "basic",
    "indicator": "Novel",
    "front": "Novel: a watchmaker named Mendel fights alongside violinist Gedalah behind enemy lines in Russia",
    "back": "If Not Now, When? (Primo Levi)",
    "work": "General / Biographical",
    "frequency": 2,
    "tags": []
  },
  {
    "type": "basic",
    "indicator": "Poem",
    "front": "Poem: recounts the 'monotonous horror' of mud in Auschwitz",
    "back": "Buna (Primo Levi)",
    "work": "General / Biographical",
    "frequency": 1,
    "tags": []
  }
]