[
  {
    "type": "basic",
    "indicator": "Novel",
    "front": "Novel: children play Cherry Tree before WWII",
    "back": "Katalin Street (Magda Szabó)",
    "work": "Katalin Street",
    "frequency": 1,
    "tags": []
  },
  {
    "type": "basic",
    "indicator": "Novel",
    "front": "Novel: Henriette Weld is shot by Nazis and observes friends as a ghost",
    "back": "Katalin Street (Magda Szabó)",
    "work": "Katalin Street",
    "frequency": 1,
    "tags": []
  },
  {
    "type": "basic",
    "indicator": "Author",
    "front": "Author: Hungarian writer who spent the 1950s teaching after being labeled a party enemy",
    "back": "Magda Szabó",
    "work": "General",
    "frequency": 1,
    "tags": []
  },
  {
    "type": "basic",
    "indicator": "Author",
    "front": "Author: wrote The Door about a writer and her housekeeper Emerence",
    "back": "Magda Szabó",
    "work": "General",
    "frequency": 1,
    "tags": []
  }
]