[
  {
    "slug": "béla_bartók",
    "topic": "Béla Bartók",
    "score": 2,
    "fwd": 2,
    "rev": 0,
    "source": "comention"
  },
  {
    "slug": "bedrich_smetana",
    "topic": "Bedrich Smetana",
    "score": 0.57,
    "source": "embedding"
  },
  {
    "slug": "antonio_vivaldi",
    "topic": "Antonio Vivaldi",
    "score": 0.55,
    "source": "embedding"
  },
  {
    "slug": "brandenburg_concertos",
    "topic": "Brandenburg Concertos",
    "score": 0.538,
    "source": "embedding"
  },
  {
    "slug": "ludwig_van_beethoven",
    "topic": "Ludwig van Beethoven",
    "score": 0.51,
    "source": "embedding"
  },
  {
    "slug": "richard_wagner",
    "topic": "Richard Wagner",
    "score": 0.507,
    "source": "embedding"
  },
  {
    "slug": "alban_berg",
    "topic": "Alban Berg",
    "score": 0.503,
    "source": "embedding"
  }
]