[
  {
    "type": "basic",
    "indicator": "Poem",
    "front": "Poem: opens 'Before you, mother Idoto, / naked I stand'",
    "back": "Heavensgate (Christopher Okigbo)",
    "work": "Heavensgate",
    "frequency": 3,
    "tags": []
  },
  {
    "type": "basic",
    "indicator": "Poem",
    "front": "Poem: speaker leans on an oilbean tree waiting for an Igbo river deity",
    "back": "Heavensgate (Christopher Okigbo)",
    "work": "Heavensgate",
    "frequency": 3,
    "tags": []
  },
  {
    "type": "basic",
    "indicator": "Poet",
    "front": "Poet: Nigerian poet who died fighting for Biafra in the Nigerian Civil War",
    "back": "Christopher Okigbo",
    "work": "General",
    "frequency": 2,
    "tags": []
  }
]