[
  {
    "slug": "john_scotus_eriugena",
    "topic": "John Scotus Eriugena",
    "score": 2,
    "fwd": 0,
    "rev": 2,
    "source": "comention"
  },
  {
    "slug": "socrates",
    "topic": "Socrates",
    "score": 2,
    "fwd": 2,
    "rev": 0,
    "source": "comention"
  },
  {
    "slug": "thomas_hobbes",
    "topic": "Thomas Hobbes",
    "score": 2,
    "fwd": 0,
    "rev": 2,
    "source": "comention"
  },
  {
    "slug": "anselm_of_canterbury",
    "topic": "Anselm of Canterbury",
    "score": 0.544,
    "source": "embedding"
  },
  {
    "slug": "saint_augustine",
    "topic": "Saint Augustine",
    "score": 0.511,
    "source": "embedding"
  }
]