[
  {
    "slug": "kingsley_amis",
    "topic": "Kingsley Amis",
    "score": 2,
    "fwd": 0,
    "rev": 2,
    "source": "comention"
  },
  {
    "slug": "raphael",
    "topic": "Raphael",
    "score": 2,
    "fwd": 0,
    "rev": 2,
    "source": "comention"
  },
  {
    "slug": "alfred_lord_tennyson",
    "topic": "Alfred Lord Tennyson",
    "score": 0.622,
    "source": "embedding"
  },
  {
    "slug": "ted_hughes",
    "topic": "Ted Hughes",
    "score": 0.569,
    "source": "embedding"
  },
  {
    "slug": "philip_larkin",
    "topic": "Philip Larkin",
    "score": 0.567,
    "source": "embedding"
  },
  {
    "slug": "w._h._auden",
    "topic": "W. H. Auden",
    "score": 0.564,
    "source": "embedding"
  },
  {
    "slug": "robert_burns",
    "topic": "Robert Burns",
    "score": 0.561,
    "source": "embedding"
  },
  {
    "slug": "thomas_chatterton",
    "topic": "Thomas Chatterton",
    "score": 0.55,
    "source": "embedding"
  }
]